testmytutor/__init__.py
testmytutor-1.0.4.dist-info/LICENSE
testmytutor-1.0.4.dist-info/METADATA
testmytutor-1.0.4.dist-info/WHEEL
testmytutor-1.0.4.dist-info/top_level.txt
testmytutor-1.0.4.dist-info/RECORD
